{"label": "phap-luat", "link": "https://vnexpress.net/thanh-tra-chinh-phu-sap-xac-minh-tai-san-ngau-nhien-30-can-bo-4516346.html", "title": "Thanh tra Chính phủ sắp xác minh tài sản ngẫu nhiên 30 cán bộ ", "description": "Thanh tra Chính phủ vừa ban hành kế hoạch chọn ngẫu nhiên 30 cán bộ, công chức của 7 bộ ngành để xác minh tài sản, thu nhập.", "content": "Kế hoạch của Thanh tra Chính phủ thực hiện theo Luật phòng chống, tham nhũng 2018 và các quy định liên quan về kiểm soát tài sản, thu nhập của người có chức vụ, quyền hạn. Thanh tra Chính phủ sẽ chọn 7 bộ ngành để xác minh là Bộ Kế hoạch và Đầu tư, Bộ Tài nguyên và Môi trường, Bộ Xây dựng, Ủy ban Quản lý vốn nhà nước tại doanh nghiệp, Tổng công ty Đầu tư và Kinh doanh vốn nhà nước, Tập đoàn Bưu chính Viễn thông Việt Nam và Tập đoàn Hóa chất Việt Nam. Tại các đơn vị này, Thanh tra Chính phủ sẽ chọn ngẫu nhiên 30 cán bộ, công chức có phụ cấp chức vụ từ 0,9 trở lên để xác minh tài sản. Trong đó, Bộ Kế hoạch và Đầu tư chọn 8 người, Bộ Tài nguyên và Môi trường 5 người, Bộ Xây dựng 5 người, các bộ ngành còn lại mỗi đơn vị 3 người. Nội dung thanh tra là xác minh tính trung thực, đầy đủ của bản kê khai tài sản và tính trung thực trong bản giải trình về nguồn gốc của tài sản thu nhập tăng thêm. Theo kế hoạch, danh sách người được xác minh sẽ lựa chọn ngẫu nhiên bằng hình thức bốc thăm. Việc bốc thăm do Thanh tra Chính phủ chủ trì, phối hợp cùng Ủy ban Kiểm tra Trung ương, Ủy ban Mặt trận Tổ quốc Việt Nam và các đơn vị liên quan. "}