{"label": "phap-luat", "link": "https://vnexpress.net/ten-cuop-bi-bat-vi-lo-tung-tich-tu-dinh-vi-4507988.html", "title": "Tên cướp bị bắt vì lộ tung tích từ định vị ", "description": "Nguyễn Hoàng Nam, 39 tuổi, giật điện thoại của người phụ nữ nhưng bị nạn nhân phát hiện từ định vị, báo cảnh sát bắt.", "content": "Ngày 6/9, Nam bị Công an quận Bình Thạnh tạm giữ hình sự về hành vi  . Theo điều tra, tối ba hôm trước Nam chạy xe máy lòng vòng tìm người sơ hở để cướp tài sản. Đến đường Điện Biên Phủ (phường 25, Bình Thạnh), anh ta phát hiện chị Ngọc, 31 tuổi, cầm iPhone 13 Promax đứng ở lề đường nên giật phăng chiếc điện thoại trị giá hơn 30 triệu đồng. Nạn nhân truy hô, song Nam đã chạy mất. Chị Ngọc kiểm tra định vị trong điện thoại, phát hiện tên cướp đang ở khu vực đường Đinh Bộ Lĩnh (phường 26, Bình Thạnh) nên trình báo cảnh sát. Tuy nhiên, vừa về đến nhà Nam tháo sim điện thoại, tắt máy, khiến cảnh sát gặp khó khi truy tìm. Tiếp tục lần theo dấu vết tên cướp từ camera an ninh xung quanh khu vực, trinh sát phát hiện Nam - nghi can có nhiều tiền án, nghiện ma tuý và vừa ra tù. Khi anh ta mang điện thoại đi bán thì bị đặc nhiệm quận Bình Thạnh mật phục, bắt giữ. "}