{"label": "phap-luat", "link": "https://vnexpress.net/dieu-tra-vi-pham-dau-thau-thiet-bi-giao-duc-o-ha-tinh-4510796.html", "title": "Điều tra vi phạm đấu thầu thiết bị giáo dục ở Hà Tĩnh ", "description": "Bộ Công an vừa khởi tố 7 bị can để điều tra các sai phạm về đấu thầu thiết bị giáo dục ở Trung tâm Tư vấn và Dịch vụ Tài chính công Hà Tĩnh.", "content": "Ngày 13/9, trung tướng Tô Ân Xô, Chánh văn phòng, người phát ngôn Bộ Công an, cho biết Cơ quan Cảnh sát điều tra (Bộ Công an) đã khởi tố, tạm giam Nguyễn Thị Thanh Tâm (Giám đốc kinh doanh Công ty Hồng Hà), Phạm Viết Anh Vũ (Giám đốc chi nhánh Hà Tĩnh Công ty Hồng Hà), Nguyễn Thành Trung (Giám đốc Công ty Phương Anh), Nguyễn Hồng Hải (Phó Giám đốc Công ty Phương Anh), Nguyễn Xuân Thiện (Công ty P&T), Dinh Quốc Tấn (Tổ trưởng Tổ đấu thầu), Lê Viết Cường (Giám đốc Trung tâm Tài chính công). Cả 7 người bị điều tra về tội  . Các quyết định và lệnh đã được VKSND Tối cao phê chuẩn. Sai phạm được xác định xảy ra tại Trung tâm Tư vấn và Dịch vụ Tài chính công Hà Tĩnh thuộc Sở Tài chính tỉnh này và các đơn vị liên quan. Cảnh sát cáo buộc, các bị can đã có hành vi trái pháp luật về đảm bảo công bằng, minh bạch trong hoạt động đấu thầu mua sắm trang thiết bị giáo dục gây thiệt hại nghiêm trọng tài sản Nhà nước. "}