{"label": "phap-luat", "link": "https://vnexpress.net/nam-sinh-16-tuoi-bi-chem-tu-vong-4506125.html", "title": "Nam sinh 16 tuổi bị chém tử vong ", "description": "Đào Việt Dũng, 16 tuổi, bị đoạt mạng bằng nhiều nhát dao sau cuộc \"nói chuyện\" với hai người bạn cùng trang lứa vào sáng 31/8.", "content": "Theo Công an xã Quốc Tuấn, huyện An Lão, nghi phạm được xác định là Ngô Anh Đức, 18 tuổi, trú thôn Cẩm Văn. 9h hôm nay, Đức và Trần Quốc Trung, 16 tuổi, đi gặp Dũng ở thôn Đồn Nham 1, xã Quốc Tuấn để giải quyết mâu thuẫn. Nhà chức trách cáo buộc khi gặp nhau, Đức cầm dao chém Dũng nhiều nhát, gây vết thương rộng ở vùng ngực. Nam sinh 16 tuổi được đưa đi cấp cứu ở Bệnh viện đa khoa huyện An Lão nhưng không qua khỏi. Đức và Trung đã bị bắt. "}