{"label": "phap-luat", "link": "https://vnexpress.net/cuop-tiem-vang-vi-muon-di-tu-4514466.html", "title": "Cướp tiệm vàng vì 'muốn đi tù' ", "description": "Trần Ngọc Sơn, 28 tuổi, khai động cơ xông vào tiệm kim hoàn Kim Huyền đập tủ kính cướp vàng ném ra ngoài đường vì \"đang buồn, muốn đi tù\".", "content": "Trưa 22/9, sau hai ngày gây án, Sơn bị Công an TP Dĩ An cáo buộc tội  Khai với cơ quan điều tra, Sơn thừa nhận tối 20/9 đã xông vào tiệm vàng Kim Huyền trên đường Nguyễn Trãi, TP Dĩ An, dùng đá đập vỡ tủ kính, vơ nữ trang ném ra đường. Sau khi gây án, anh ta không bỏ chạy mà ngồi trước cửa tiệm, bị người dân bắt giao cho công an. Lý giải về hành vi của mình, Sơn khai do buồn chán cuộc sống, từng có ý định tự tử. Khi đi qua tiệm vàng, anh ta nảy sinh ý định \"muốn đi tù\" nên đã xông vào cướp. Cảnh sát đang làm rõ lời khai của nghi phạm, chưa kết luận nguyên nhân anh ta gây án. Chủ tiệm Kim Huyền cho biết, Sơn đã lấy 18 nhẫn vàng trị giá 57 triệu đồng ném ra đường. Hiện, cửa hàng thu lại được 8 chiếc nhẫn có giá 25 triệu. "}